odoo/addons/purchase_requisition_order_remaining_qty/README.rst
odoo/addons/purchase_requisition_order_remaining_qty/__init__.py
odoo/addons/purchase_requisition_order_remaining_qty/__manifest__.py
odoo/addons/purchase_requisition_order_remaining_qty/i18n/es.po
odoo/addons/purchase_requisition_order_remaining_qty/i18n/it.po
odoo/addons/purchase_requisition_order_remaining_qty/i18n/purchase_requisition_order_remaining_qty.pot
odoo/addons/purchase_requisition_order_remaining_qty/models/__init__.py
odoo/addons/purchase_requisition_order_remaining_qty/models/purchase_order.py
odoo/addons/purchase_requisition_order_remaining_qty/models/purchase_requisition_line.py
odoo/addons/purchase_requisition_order_remaining_qty/models/purchase_requisition_type.py
odoo/addons/purchase_requisition_order_remaining_qty/readme/CONFIGURE.md
odoo/addons/purchase_requisition_order_remaining_qty/readme/CONTRIBUTORS.md
odoo/addons/purchase_requisition_order_remaining_qty/readme/DESCRIPTION.md
odoo/addons/purchase_requisition_order_remaining_qty/readme/USAGE.md
odoo/addons/purchase_requisition_order_remaining_qty/static/description/icon.png
odoo/addons/purchase_requisition_order_remaining_qty/static/description/index.html
odoo/addons/purchase_requisition_order_remaining_qty/tests/__init__.py
odoo/addons/purchase_requisition_order_remaining_qty/tests/test_purchase_requisition_order_remaining_qty.py
odoo/addons/purchase_requisition_order_remaining_qty/views/purchase_requisition_view.xml
odoo_addon_purchase_requisition_order_remaining_qty-17.0.1.0.0.4.dist-info/METADATA
odoo_addon_purchase_requisition_order_remaining_qty-17.0.1.0.0.4.dist-info/WHEEL
odoo_addon_purchase_requisition_order_remaining_qty-17.0.1.0.0.4.dist-info/top_level.txt
odoo_addon_purchase_requisition_order_remaining_qty-17.0.1.0.0.4.dist-info/RECORD
